pycs/__init__.py
pycs/errors.py
pycs/full_key_value.py
pycs/helpers.py
pycs/interfaces.py
pycs/leaf.py
pycs/node.py
pycs/transforms.py
pycs/utils.py
pycs-6.0.0.dist-info/entry_points.txt
pycs-6.0.0.dist-info/LICENSE
pycs-6.0.0.dist-info/WHEEL
pycs-6.0.0.dist-info/METADATA
pycs-6.0.0.dist-info/RECORD
