Metadata-Version: 2.1
Name: pycs
Version: 6.0.0
Summary: Python Configuration System
Author: Anton Vasilev, Artem Vasenin, Vladimir Mikhaylov
Maintainer-email: Artem Vasenin <vasart169@gmail.com>
Requires-Python: >=3.9
Requires-Dist: isort
Requires-Dist: pyyaml
Requires-Dist: sample-helper-aws-appconfig ; extra == "aws"
Requires-Dist: black ; extra == "dev"
Requires-Dist: pre-commit ; extra == "dev"
Requires-Dist: pycs[test,aws] ; extra == "dev"
Requires-Dist: ruff ; extra == "dev"
Requires-Dist: pytest ; extra == "test"
Requires-Dist: pytest-cov ; extra == "test"
Requires-Dist: types-pyyaml ; extra == "test"
Project-URL: Home, https://github.com/Rizhiy/pycs
Provides-Extra: aws
Provides-Extra: dev
Provides-Extra: test
